mbonig/sqs_redrive/__init__.py
mbonig/sqs_redrive/py.typed
mbonig/sqs_redrive/_jsii/__init__.py
mbonig/sqs_redrive/_jsii/sqs-redrive@1.85.0.jsii.tgz
mbonig.sqs_redrive-1.85.0.data/scripts/sqs-redrive-construct
mbonig.sqs_redrive-1.85.0.dist-info/METADATA
mbonig.sqs_redrive-1.85.0.dist-info/WHEEL
mbonig.sqs_redrive-1.85.0.dist-info/top_level.txt
mbonig.sqs_redrive-1.85.0.dist-info/RECORD
