Metadata-Version: 2.1
Name: mbonig.sqs-redrive
Version: 1.85.0
Summary: A redrive construct to use with an SQS queue and it's dead letter queue
Home-page: https://github.com/mbonig/sqs-redrive
Author: Matthew Bonig<matthew.bonig@gmail.com>
License: MIT
Project-URL: Source, https://github.com/mbonig/sqs-redrive
Platform: UNKNOWN
Classifier: Intended Audience :: Developers
Classifier: Operating System :: OS Independent
Classifier: Programming Language :: JavaScript
Classifier: Programming Language :: Python :: 3 :: Only
Classifier: Programming Language :: Python :: 3.6
Classifier: Programming Language :: Python :: 3.7
Classifier: Programming Language :: Python :: 3.8
Classifier: Programming Language :: Python :: 3.9
Classifier: Typing :: Typed
Classifier: Development Status :: 5 - Production/Stable
Classifier: License :: OSI Approved
Requires-Python: >=3.6
Requires-Dist: aws-cdk.aws-lambda-nodejs (<2.0.0,>=1.85.0)
Requires-Dist: aws-cdk.aws-lambda (<2.0.0,>=1.85.0)
Requires-Dist: aws-cdk.aws-sqs (<2.0.0,>=1.85.0)
Requires-Dist: aws-cdk.core (<2.0.0,>=1.85.0)
Requires-Dist: constructs (<4.0.0,>=3.2.27)
Requires-Dist: jsii (<2.0.0,>=1.17.1)
Requires-Dist: publication (>=0.0.3)
